isetlx/__init__.py
isetlx/__main__.py
isetlx/install.py
isetlx/kernel.py
isetlx/logo-32x32.png
isetlx/logo-64x64.png
isetlx-1.0.dist-info/LICENSE
isetlx-1.0.dist-info/METADATA
isetlx-1.0.dist-info/WHEEL
isetlx-1.0.dist-info/top_level.txt
isetlx-1.0.dist-info/RECORD
