Metadata-Version: 2.1
Name: isetlx
Version: 1.0
Summary: Python wrapper kernel for SetlX
Home-page: https://github.com/1b15/iSetlX
Author: Georg Reich
Author-email: UNKNOWN
License: UNKNOWN
Platform: UNKNOWN
Classifier: Intended Audience :: Developers
Classifier: License :: OSI Approved :: MIT License
Classifier: Programming Language :: Python :: 3
Requires-Dist: jupyter-client
Requires-Dist: IPython
Requires-Dist: ipykernel
